Workbook

Sheet Summary
A1: Labourmax-HR statutory verification
A2: THIS WORKBOOK IS A WORK AID AND NEVER A SOURCE OF TRUTH. The fixtures in reference/ are the loaded data and docs/DECISIONS.md is the register; importverification records that a figure was checked and can never change one.
A4: By source document
A5: Source document | B5: Figures | C5: Checked | D5: Queried | E5: Outstanding
A6: BCCCI (KwaZulu-Natal) Main Collective Agreement, GN R.7296 in GG 54412, 27 March 2026 | B6: 23 | C6: =COUNTIFS(Figures!$A:$A,$A6,Figures!$K:$K,"Y") | D6: =COUNTIFS(Figures!$A:$A,$A6,Figures!$K:$K,"QUERY") | E6: =$B6-$C6-$D6
A7: Bargaining Council for the Contract Cleaning Services Industry (KwaZulu-Natal) Main Collective Agreement, GN R.7296 in Government Gazette 54412, 27 March 2026 | B7: 67 | C7: =COUNTIFS(Figures!$A:$A,$A7,Figures!$K:$K,"Y") | D7: =COUNTIFS(Figures!$A:$A,$A7,Figures!$K:$K,"QUERY") | E7: =$B7-$C7-$D7
A8: Basic Conditions of Employment Act 75 of 1997 | B8: 86 | C8: =COUNTIFS(Figures!$A:$A,$A8,Figures!$K:$K,"Y") | D8: =COUNTIFS(Figures!$A:$A,$A8,Figures!$K:$K,"QUERY") | E8: =$B8-$C8-$D8
A9: Compensation Fund maximum amount of earnings, 2026/2027 assessment year (1 March 2026 - 28 February 2027) | B9: 2 | C9: =COUNTIFS(Figures!$A:$A,$A9,Figures!$K:$K,"Y") | D9: =COUNTIFS(Figures!$A:$A,$A9,Figures!$K:$K,"QUERY") | E9: =$B9-$C9-$D9
A10: Determination under s6(2) of the Unemployment Insurance Contributions Act 4 of 2002, Government Gazette 44641 of 28 May 2021, effective 1 June 2021 | B10: 2 | C10: =COUNTIFS(Figures!$A:$A,$A10,Figures!$K:$K,"Y") | D10: =COUNTIFS(Figures!$A:$A,$A10,Figures!$K:$K,"QUERY") | E10: =$B10-$C10-$D10
A11: GN 5970, GG 52232, March 2025 (Basic Conditions of Employment Act 75 of 1997, s6(3)) | B11: 2 | C11: =COUNTIFS(Figures!$A:$A,$A11,Figures!$K:$K,"Y") | D11: =COUNTIFS(Figures!$A:$A,$A11,Figures!$K:$K,"QUERY") | E11: =$B11-$C11-$D11
A12: GN 7384, GG 54544, 17 April 2026 (Basic Conditions of Employment Act 75 of 1997, s6(3)) | B12: 2 | C12: =COUNTIFS(Figures!$A:$A,$A12,Figures!$K:$K,"Y") | D12: =COUNTIFS(Figures!$A:$A,$A12,Figures!$K:$K,"QUERY") | E12: =$B12-$C12-$D12
A13: GN R.7083, GG 54075, 3 February 2026 (National Minimum Wage Act 9 of 2018) | B13: 8 | C13: =COUNTIFS(Figures!$A:$A,$A13,Figures!$K:$K,"Y") | D13: =COUNTIFS(Figures!$A:$A,$A13,Figures!$K:$K,"QUERY") | E13: =$B13-$C13-$D13
A14: Public Holidays Act 36 of 1994 | B14: 75 | C14: =COUNTIFS(Figures!$A:$A,$A14,Figures!$K:$K,"Y") | D14: =COUNTIFS(Figures!$A:$A,$A14,Figures!$K:$K,"QUERY") | E14: =$B14-$C14-$D14
A15: SARS Guide for Codes Applicable to Employees Tax Certificates (PAYE-AE-06-G06), 2026 issue | B15: 114 | C15: =COUNTIFS(Figures!$A:$A,$A15,Figures!$K:$K,"Y") | D15: =COUNTIFS(Figures!$A:$A,$A15,Figures!$K:$K,"QUERY") | E15: =$B15-$C15-$D15
A16: SARS Medical Tax Credit Rates, 2027 tax year (1 March 2026 - 28 February 2027) | B16: 3 | C16: =COUNTIFS(Figures!$A:$A,$A16,Figures!$K:$K,"Y") | D16: =COUNTIFS(Figures!$A:$A,$A16,Figures!$K:$K,"QUERY") | E16: =$B16-$C16-$D16
A17: SARS PAYE-AE-06-G06, Guide for Codes Applicable to Employees Tax Certificates 2026, revision 13, effective 19 September 2025 | B17: 12 | C17: =COUNTIFS(Figures!$A:$A,$A17,Figures!$K:$K,"Y") | D17: =COUNTIFS(Figures!$A:$A,$A17,Figures!$K:$K,"QUERY") | E17: =$B17-$C17-$D17
... A24: Van Wyk v Minister of Employment and Labour (CCT 308/23) [2025] ZACC 20 (3 October 2025) | B24: 7 | C24: =COUNTIFS(Figures!$A:$A,$A24,Figures!$K:$K,"Y") | D24: =COUNTIFS(Figures!$A:$A,$A24,Figures!$K:$K,"QUERY") | E24: =$B24-$C24-$D24
A25: TOTAL | B25: 582 | C25: =SUM(C6:C24) | D25: =SUM(D6:D24) | E25: =SUM(E6:E24)
A27: By reference version
A28: Reference version | B28: Figures | C28: Checked | D28: Queried | E28: Verified? | F28: Loaded by | G28: barkofs@gmail.com may verify?
A29: REF-2026.03.01-BANKS | B29: 0 | C29: =COUNTIFS(Figures!$D:$D,$A29,Figures!$K:$K,"Y") | D29: =COUNTIFS(Figures!$D:$D,$A29,Figures!$K:$K,"QUERY") | E29: NOT verified | F29: dev-loader@labourmax.invalid | G29: yes
A30: REF-2026.03.01-CODES | B30: 114 | C30: =COUNTIFS(Figures!$D:$D,$A30,Figures!$K:$K,"Y") | D30: =COUNTIFS(Figures!$D:$D,$A30,Figures!$K:$K,"QUERY") | E30: NOT verified | F30: dev-loader@labourmax.invalid | G30: yes
A31: REF-2026.03.01-EMPLOYMENT | B31: 2 | C31: =COUNTIFS(Figures!$D:$D,$A31,Figures!$K:$K,"Y") | D31: =COUNTIFS(Figures!$D:$D,$A31,Figures!$K:$K,"QUERY") | E31: NOT verified | F31: dev-loader@labourmax.invalid | G31: yes
A32: REF-2026.03.01-LEAVE | B32: 2 | C32: =COUNTIFS(Figures!$D:$D,$A32,Figures!$K:$K,"Y") | D32: =COUNTIFS(Figures!$D:$D,$A32,Figures!$K:$K,"QUERY") | E32: NOT verified | F32: dev-loader@labourmax.invalid | G32: yes
A33: REF-2026.03.01-LEAVE-PAY | B33: 2 | C33: =COUNTIFS(Figures!$D:$D,$A33,Figures!$K:$K,"Y") | D33: =COUNTIFS(Figures!$D:$D,$A33,Figures!$K:$K,"QUERY") | E33: NOT verified | F33: dev-loader@labourmax.invalid | G33: yes
A34: REF-2026.03.01-LUMPSUM | B34: 12 | C34: =COUNTIFS(Figures!$D:$D,$A34,Figures!$K:$K,"Y") | D34: =COUNTIFS(Figures!$D:$D,$A34,Figures!$K:$K,"QUERY") | E34: NOT verified | F34: dev-loader@labourmax.invalid | G34: yes
A35: REF-2026.03.01-NOTICE-BANDS-3 | B35: 54 | C35: =COUNTIFS(Figures!$D:$D,$A35,Figures!$K:$K,"Y") | D35: =COUNTIFS(Figures!$D:$D,$A35,Figures!$K:$K,"QUERY") | E35: NOT verified | F35: dev-loader@labourmax.invalid | G35: yes
A36: REF-2026.03.01-PARENTAL-2 | B36: 7 | C36: =COUNTIFS(Figures!$D:$D,$A36,Figures!$K:$K,"Y") | D36: =COUNTIFS(Figures!$D:$D,$A36,Figures!$K:$K,"QUERY") | E36: NOT verified | F36: dev-loader@labourmax.invalid | G36: yes
A37: REF-2026.03.01-r2 | B37: 140 | C37: =COUNTIFS(Figures!$D:$D,$A37,Figures!$K:$K,"Y") | D37: =COUNTIFS(Figures!$D:$D,$A37,Figures!$K:$K,"QUERY") | E37: NOT verified | F37: dev-loader@labourmax.invalid | G37: yes
A38: REF-2026.03.01-REMUNERATION | B38: 2 | C38: =COUNTIFS(Figures!$D:$D,$A38,Figures!$K:$K,"Y") | D38: =COUNTIFS(Figures!$D:$D,$A38,Figures!$K:$K,"QUERY") | E38: NOT verified | F38: dev-loader@labourmax.invalid | G38: yes
A39: REF-2026.03.01-RULES-r4 | B39: 101 | C39: =COUNTIFS(Figures!$D:$D,$A39,Figures!$K:$K,"Y") | D39: =COUNTIFS(Figures!$D:$D,$A39,Figures!$K:$K,"QUERY") | E39: NOT verified | F39: dev-loader@labourmax.invalid | G39: yes
A40: REF-2026.03.01-SD1-r4 | B40: 52 | C40: =COUNTIFS(Figures!$D:$D,$A40,Figures!$K:$K,"Y") | D40: =COUNTIFS(Figures!$D:$D,$A40,Figures!$K:$K,"QUERY") | E40: NOT verified | F40: dev-loader@labourmax.invalid | G40: yes
... A46: REF-2026.04.01-BCCCI-RULES-r2 | B46: 56 | C46: =COUNTIFS(Figures!$D:$D,$A46,Figures!$K:$K,"Y") | D46: =COUNTIFS(Figures!$D:$D,$A46,Figures!$K:$K,"QUERY") | E46: MACHINE ONLY — still needs a human | F46: dev-loader@labourmax.invalid | G46: yes
A48: MACHINE ONLY means verified by claude-verification@labourmax.invalid, which is a development identity and not a person. Those versions need a human pass exactly like the others — they are not done.

Sheet Figures
A1: Source document | B1: Clause / section | C1: Source URL | D1: Reference version | E1: Table | F1: What it is | G1: Value as loaded | H1: Effective from | I1: Effective to | J1: Row key | K1: Checked | L1: Checked by | M1: Date checked | N1: Note
A2: BCCCI (KwaZulu-Natal) Main Collective Agreement, GN R.7296 in GG 54412, 27 March 2026 | B2: clause 21.1(b)(i) | D2: REF-2026.04.01-BCCCI-NOTICE-r2 | E2: termination_notice_band | F2: Notice band 1 — CONTRACT_CLEANING / AREA_B, 0.00 weeks to 4.00 weeks — is contested | G2: No | J2: termination_notice_band:8:is_contested
A3: BCCCI (KwaZulu-Natal) Main Collective Agreement, GN R.7296 in GG 54412, 27 March 2026 | B3: clause 21.1(b)(i) | D3: REF-2026.04.01-BCCCI-NOTICE-r2 | E3: termination_notice_band | F3: Notice band 1 — CONTRACT_CLEANING / AREA_B, 0.00 weeks to 4.00 weeks — notice unit | G3: Days | J3: termination_notice_band:8:notice_unit
A4: BCCCI (KwaZulu-Natal) Main Collective Agreement, GN R.7296 in GG 54412, 27 March 2026 | B4: clause 21.1(b)(i) | D4: REF-2026.04.01-BCCCI-NOTICE-r2 | E4: termination_notice_band | F4: Notice band 1 — CONTRACT_CLEANING / AREA_B, 0.00 weeks to 4.00 weeks — notice value | G4: 1,00 | J4: termination_notice_band:8:notice_value
A5: BCCCI (KwaZulu-Natal) Main Collective Agreement, GN R.7296 in GG 54412, 27 March 2026 | B5: clause 21.1(b)(i) | D5: REF-2026.04.01-BCCCI-NOTICE-r2 | E5: termination_notice_band | F5: Notice band 1 — CONTRACT_CLEANING / AREA_B, 0.00 weeks to 4.00 weeks — service from inclusive | G5: Yes | J5: termination_notice_band:8:service_from_inclusive
A6: BCCCI (KwaZulu-Natal) Main Collective Agreement, GN R.7296 in GG 54412, 27 March 2026 | B6: clause 21.1(b)(i) | D6: REF-2026.04.01-BCCCI-NOTICE-r2 | E6: termination_notice_band | F6: Notice band 1 — CONTRACT_CLEANING / AREA_B, 0.00 weeks to 4.00 weeks — service from unit | G6: Weeks | J6: termination_notice_band:8:service_from_unit
A7: BCCCI (KwaZulu-Natal) Main Collective Agreement, GN R.7296 in GG 54412, 27 March 2026 | B7: clause 21.1(b)(i) | D7: REF-2026.04.01-BCCCI-NOTICE-r2 | E7: termination_notice_band | F7: Notice band 1 — CONTRACT_CLEANING / AREA_B, 0.00 weeks to 4.00 weeks — service from value | G7: 0,00 | J7: termination_notice_band:8:service_from_value
A8: BCCCI (KwaZulu-Natal) Main Collective Agreement, GN R.7296 in GG 54412, 27 March 2026 | B8: clause 21.1(b)(i) | D8: REF-2026.04.01-BCCCI-NOTICE-r2 | E8: termination_notice_band | F8: Notice band 1 — CONTRACT_CLEANING / AREA_B, 0.00 weeks to 4.00 weeks — service to inclusive | G8: Yes | J8: termination_notice_band:8:service_to_inclusive
A9: BCCCI (KwaZulu-Natal) Main Collective Agreement, GN R.7296 in GG 54412, 27 March 2026 | B9: clause 21.1(b)(i) | D9: REF-2026.04.01-BCCCI-NOTICE-r2 | E9: termination_notice_band | F9: Notice band 1 — CONTRACT_CLEANING / AREA_B, 0.00 weeks to 4.00 weeks — service to unit | G9: Weeks | J9: termination_notice_band:8:service_to_unit
A10: BCCCI (KwaZulu-Natal) Main Collective Agreement, GN R.7296 in GG 54412, 27 March 2026 | B10: clause 21.1(b)(i) | D10: REF-2026.04.01-BCCCI-NOTICE-r2 | E10: termination_notice_band | F10: Notice band 1 — CONTRACT_CLEANING / AREA_B, 0.00 weeks to 4.00 weeks — service to value | G10: 4,00 | J10: termination_notice_band:8:service_to_value
A11: BCCCI (KwaZulu-Natal) Main Collective Agreement, GN R.7296 in GG 54412, 27 March 2026 | B11: clause 21.1(b), second 'i)' and 'ii)' as published | D11: REF-2026.04.01-BCCCI-NOTICE-r2 | E11: termination_notice_band | F11: Notice band 2 — CONTRACT_CLEANING / AREA_B, 4.00 weeks to 6.00 months — contested reason | G11: TWO LIMBS, TWO ANSWERS. The clause says both "Not less than two weeks notice shall be given after the first four weeks of such employment" and "Not less than one weeks notice shall be given to an employee whilst on probation, as defined, for the period of employment between 4 weeks as in sub clause (i) above and six months". Probation is defined in clause 3 as a maximum of four months, so an employee between four weeks and six months falls under both. Clause 21.2(a) prices only the one working day and the two weeks, giving no payment in lieu for the one-week probation notice, so the payment clause does not settle it either. | J11: termination_notice_band:9:contested_reason
A12: BCCCI (KwaZulu-Natal) Main Collective Agreement, GN R.7296 in GG 54412, 27 March 2026 | B12: clause 21.1(b), second 'i)' and 'ii)' as published | D12: REF-2026.04.01-BCCCI-NOTICE-r2 | E12: termination_notice_band | F12: Notice band 2 — CONTRACT_CLEANING / AREA_B, 4.00 weeks to 6.00 months — is contested | G12: Yes | J12: termination_notice_band:9:is_contested
A13: BCCCI (KwaZulu-Natal) Main Collective Agreement, GN R.7296 in GG 54412, 27 March 2026 | B13: clause 21.1(b), second 'i)' and 'ii)' as published | D13: REF-2026.04.01-BCCCI-NOTICE-r2 | E13: termination_notice_band | F13: Notice band 2 — CONTRACT_CLEANING / AREA_B, 4.00 weeks to 6.00 months — service from inclusive | G13: No | J13: termination_notice_band:9:service_from_inclusive
... A24: BCCCI (KwaZulu-Natal) Main Collective Agreement, GN R.7296 in GG 54412, 27 March 2026 | B24: clause 21.1(b), second 'i)' as published | D24: REF-2026.04.01-BCCCI-NOTICE-r2 | E24: termination_notice_band | F24: Notice band 3 — CONTRACT_CLEANING / AREA_B, 6.00 months to open-ended — service from value | G24: 6,00 | J24: termination_notice_band:10:service_from_value
A25: Bargaining Council for the Contract Cleaning Services Industry (KwaZulu-Natal) Main Collective Agreement, GN R.7296 in Government Gazette 54412, 27 March 2026 | B25: clause 13.2 | C25: https://www.gov.za/sites/default/files/gcis_document/202603/54412rg11965gon7296.pdf | D25: REF-2026.04.01-BCCCI-MATERNITY | E25: statutory_parameter | F25: Statutory parameter PRENATAL_CLINIC_PAID_DAYS_PER_MONTH (CONTRACT_CLEANING / AREA_B) — unit | G25: Days | H25: 2026-04-01 | J25: statutory_parameter:17:unit
A26: Bargaining Council for the Contract Cleaning Services Industry (KwaZulu-Natal) Main Collective Agreement, GN R.7296 in Government Gazette 54412, 27 March 2026 | B26: clause 13.2 | C26: https://www.gov.za/sites/default/files/gcis_document/202603/54412rg11965gon7296.pdf | D26: REF-2026.04.01-BCCCI-MATERNITY | E26: statutory_parameter | F26: Statutory parameter PRENATAL_CLINIC_PAID_DAYS_PER_MONTH (CONTRACT_CLEANING / AREA_B) — value | G26: 1,000000 | H26: 2026-04-01 | J26: statutory_parameter:17:value_numeric
A27: Bargaining Council for the Contract Cleaning Services Industry (KwaZulu-Natal) Main Collective Agreement, GN R.7296 in Government Gazette 54412, 27 March 2026 | B27: clause 13.2 | C27: https://www.gov.za/sites/default/files/gcis_document/202603/54412rg11965gon7296.pdf | D27: REF-2026.04.01-BCCCI-MATERNITY | E27: statutory_parameter | F27: Statutory parameter PRENATAL_CLINIC_MONTHS_BEFORE_BIRTH (CONTRACT_CLEANING / AREA_B) — unit | G27: Months | H27: 2026-04-01 | J27: statutory_parameter:18:unit
A28: Bargaining Council for the Contract Cleaning Services Industry (KwaZulu-Natal) Main Collective Agreement, GN R.7296 in Government Gazette 54412, 27 March 2026 | B28: clause 13.2 | C28: https://www.gov.za/sites/default/files/gcis_document/202603/54412rg11965gon7296.pdf | D28: REF-2026.04.01-BCCCI-MATERNITY | E28: statutory_parameter | F28: Statutory parameter PRENATAL_CLINIC_MONTHS_BEFORE_BIRTH (CONTRACT_CLEANING / AREA_B) — value | G28: 3,000000 | H28: 2026-04-01 | J28: statutory_parameter:18:value_numeric
A29: Bargaining Council for the Contract Cleaning Services Industry (KwaZulu-Natal) Main Collective Agreement, GN R.7296 in Government Gazette 54412, 27 March 2026 | B29: clause 13.4(a) | C29: https://www.gov.za/sites/default/files/gcis_document/202603/54412rg11965gon7296.pdf | D29: REF-2026.04.01-BCCCI-MATERNITY | E29: statutory_parameter | F29: Statutory parameter MATERNITY_RETURN_PAYMENT_MONTH_DIVISOR (CONTRACT_CLEANING / AREA_B) — unit | G29: Ratio | H29: 2026-04-01 | J29: statutory_parameter:19:unit
A30: Bargaining Council for the Contract Cleaning Services Industry (KwaZulu-Natal) Main Collective Agreement, GN R.7296 in Government Gazette 54412, 27 March 2026 | B30: clause 13.4(a) | C30: https://www.gov.za/sites/default/files/gcis_document/202603/54412rg11965gon7296.pdf | D30: REF-2026.04.01-BCCCI-MATERNITY | E30: statutory_parameter | F30: Statutory parameter MATERNITY_RETURN_PAYMENT_MONTH_DIVISOR (CONTRACT_CLEANING / AREA_B) — value | G30: 3,000000 | H30: 2026-04-01 | J30: statutory_parameter:19:value_numeric
A31: Bargaining Council for the Contract Cleaning Services Industry (KwaZulu-Natal) Main Collective Agreement, GN R.7296 in Government Gazette 54412, 27 March 2026 | B31: clause 3, definition of 'monthly wage' | C31: https://www.gov.za/sites/default/files/gcis_document/202603/54412rg11965gon7296.pdf | D31: REF-2026.04.01-BCCCI | E31: statutory_parameter | F31: Statutory parameter MONTHLY_TO_WEEKLY_FACTOR (CONTRACT_CLEANING / AREA_B) — unit | G31: Ratio | H31: 2026-04-01 | J31: statutory_parameter:16:unit
A32: Bargaining Council for the Contract Cleaning Services Industry (KwaZulu-Natal) Main Collective Agreement, GN R.7296 in Government Gazette 54412, 27 March 2026 | B32: clause 3, definition of 'monthly wage' | C32: https://www.gov.za/sites/default/files/gcis_document/202603/54412rg11965gon7296.pdf | D32: REF-2026.04.01-BCCCI | E32: statutory_parameter | F32: Statutory parameter MONTHLY_TO_WEEKLY_FACTOR (CONTRACT_CLEANING / AREA_B) — value | G32: 4,330000 | H32: 2026-04-01 | J32: statutory_parameter:16:value_numeric
A33: Bargaining Council for the Contract Cleaning Services Industry (KwaZulu-Natal) Main Collective Agreement, GN R.7296 in Government Gazette 54412, 27 March 2026 | B33: clause 4.1(a)(i) | C33: https://www.gov.za/sites/default/files/gcis_document/202603/54412rg11965gon7296.pdf | D33: REF-2026.04.01-BCCCI | E33: minimum_wage_rate | F33: Minimum wage — CONTRACT_CLEANING / AREA_B, all hours — hourly rate | G33: R 32,40 | H33: 2026-04-01 | I33: 2027-03-01 | J33: minimum_wage_rate:5:hourly_rate
A34: Bargaining Council for the Contract Cleaning Services Industry (KwaZulu-Natal) Main Collective Agreement, GN R.7296 in Government Gazette 54412, 27 March 2026 | B34: clause 4.1(a)(ii) | C34: https://www.gov.za/sites/default/files/gcis_document/202603/54412rg11965gon7296.pdf | D34: REF-2026.04.01-BCCCI | E34: minimum_wage_rate | F34: Minimum wage — CONTRACT_CLEANING / AREA_B, all hours — hourly rate | G34: R 34,02 | H34: 2027-03-01 | I34: 2028-03-01 | J34: minimum_wage_rate:6:hourly_rate
A35: Bargaining Council for the Contract Cleaning Services Industry (KwaZulu-Natal) Main Collective Agreement, GN R.7296 in Government Gazette 54412, 27 March 2026 | B35: clause 4.1(a)(iii) | C35: https://www.gov.za/sites/default/files/gcis_document/202603/54412rg11965gon7296.pdf | D35: REF-2026.04.01-BCCCI | E35: minimum_wage_rate | F35: Minimum wage — CONTRACT_CLEANING / AREA_B, all hours — hourly rate | G35: R 35,72 | H35: 2028-03-01 | J35: minimum_wage_rate:7:hourly_rate
A36: Bargaining Council for the Contract Cleaning Services Industry (KwaZulu-Natal) Main Collective Agreement, GN R.7296 in Government Gazette 54412, 27 March 2026 | B36: clauses 3, 4.3, 5, 8, 11, 16 and 17 | D36: REF-2026.04.01-BCCCI-RULES-r2 | E36: working_time_rule_set | F36: Working time rules — CONTRACT_CLEANING / AREA_B — accommodation deduction capped | G36: No | H36: 2026-04-01 | J36: working_time_rule_set:4:accommodation_deduction_capped
A37: Bargaining Council for the Contract Cleaning Services Industry (KwaZulu-Natal) Main Collective Agreement, GN R.7296 in Government Gazette 54412, 27 March 2026 | B37: clauses 3, 4.3, 5, 8, 11, 16 and 17 | D37: REF-2026.04.01-BCCCI-RULES-r2 | E37: working_time_rule_set | F37: Working time rules — CONTRACT_CLEANING / AREA_B — daily rest hours | G37: 12 | H37: 2026-04-01 | J37: working_time_rule_set:4:daily_rest_hours
A38: Bargaining Council for the Contract Cleaning Services Industry (KwaZulu-Natal) Main Collective Agreement, GN R.7296 in Government Gazette 54412, 27 March 2026 | B38: clauses 3, 4.3, 5, 8, 11, 16 and 17 | D38: REF-2026.04.01-BCCCI-RULES-r2 | E38: working_time_rule_set | F38: Working time rules — CONTRACT_CLEANING / AREA_B — max overtime hours per day | G38: 3,00 | H38: 2026-04-01 | J38: working_time_rule_set:4:max_overtime_hours_per_day
A39: Bargaining Council for the Contract Cleaning Services Industry (KwaZulu-Natal) Main Collective Agreement, GN R.7296 in Government Gazette 54412, 27 March 2026 | B39: clauses 3, 4.3, 5, 8, 11, 16 and 17 | D39: REF-2026.04.01-BCCCI-RULES-r2 | E39: working_time_rule_set | F39: Working time rules — CONTRACT_CLEANING / AREA_B — max overtime hours per week | G39: 10,00 | H39: 2026-04-01 | J39: working_time_rule_set:4:max_overtime_hours_per_week
A40: Bargaining Council for the Contract Cleaning Services Industry (KwaZulu-Natal) Main Collective Agreement, GN R.7296 in Government Gazette 54412, 27 March 2026 | B40: clauses 3, 4.3, 5, 8, 11, 16 and 17 | D40: REF-2026.04.01-BCCCI-RULES-r2 | E40: working_time_rule_set | F40: Working time rules — CONTRACT_CLEANING / AREA_B — meal interval after hours | G40: 5,00 | H40: 2026-04-01 | J40: working_time_rule_set:4:meal_interval_after_hours
A41: Bargaining Council for the Contract Cleaning Services Industry (KwaZulu-Natal) Main Collective Agreement, GN R.7296 in Government Gazette 54412, 27 March 2026 | B41: clauses 3, 4.3, 5, 8, 11, 16 and 17 | D41: REF-2026.04.01-BCCCI-RULES-r2 | E41: working_time_rule_set | F41: Working time rules — CONTRACT_CLEANING / AREA_B — meal interval minutes | G41: 60 | H41: 2026-04-01 | J41: working_time_rule_set:4:meal_interval_minutes
A42: Bargaining Council for the Contract Cleaning Services Industry (KwaZulu-Natal) Main Collective Agreement, GN R.7296 in Government Gazette 54412, 27 March 2026 | B42: clauses 3, 4.3, 5, 8, 11, 16 and 17 | D42: REF-2026.04.01-BCCCI-RULES-r2 | E42: working_time_rule_set | F42: Working time rules — CONTRACT_CLEANING / AREA_B — min paid hours per day | G42: 6,00 | H42: 2026-04-01 | J42: working_time_rule_set:4:min_paid_hours_per_day
A43: Bargaining Council for the Contract Cleaning Services Industry (KwaZulu-Natal) Main Collective Agreement, GN R.7296 in Government Gazette 54412, 27 March 2026 | B43: clauses 3, 4.3, 5, 8, 11, 16 and 17 | D43: REF-2026.04.01-BCCCI-RULES-r2 | E43: working_time_rule_set | F43: Working time rules — CONTRACT_CLEANING / AREA_B — night allowance type | G43: A percentage of the hourly wage | H43: 2026-04-01 | J43: working_time_rule_set:4:night_allowance_type
A44: Bargaining Council for the Contract Cleaning Services Industry (KwaZulu-Natal) Main Collective Agreement, GN R.7296 in Government Gazette 54412, 27 March 2026 | B44: clauses 3, 4.3, 5, 8, 11, 16 and 17 | D44: REF-2026.04.01-BCCCI-RULES-r2 | E44: working_time_rule_set | F44: Working time rules — CONTRACT_CLEANING / AREA_B — night allowance value | G44: 10,0000 | H44: 2026-04-01 | J44: working_time_rule_set:4:night_allowance_value
A45: Bargaining Council for the Contract Cleaning Services Industry (KwaZulu-Natal) Main Collective Agreement, GN R.7296 in Government Gazette 54412, 27 March 2026 | B45: clauses 3, 4.3, 5, 8, 11, 16 and 17 | D45: REF-2026.04.01-BCCCI-RULES-r2 | E45: working_time_rule_set | F45: Working time rules — CONTRACT_CLEANING / AREA_B — night work end time | G45: 06:00:00 | H45: 2026-04-01 | J45: working_time_rule_set:4:night_work_end_time
A46: Bargaining Council for the Contract Cleaning Services Industry (KwaZulu-Natal) Main Collective Agreement, GN R.7296 in Government Gazette 54412, 27 March 2026 | B46: clauses 3, 4.3, 5, 8, 11, 16 and 17 | D46: REF-2026.04.01-BCCCI-RULES-r2 | E46: working_time_rule_set | F46: Working time rules — CONTRACT_CLEANING / AREA_B — night work start time | G46: 18:00:00 | H46: 2026-04-01 | J46: working_time_rule_set:4:night_work_start_time
A47: Bargaining Council for the Contract Cleaning Services Industry (KwaZulu-Natal) Main Collective Agreement, GN R.7296 in Government Gazette 54412, 27 March 2026 | B47: clauses 3, 4.3, 5, 8, 11, 16 and 17 | D47: REF-2026.04.01-BCCCI-RULES-r2 | E47: working_time_rule_set | F47: Working time rules — CONTRACT_CLEANING / AREA_B — ordinary hours per day 5day | G47: 9,00 | H47: 2026-04-01 | J47: working_time_rule_set:4:ordinary_hours_per_day_5day
... A91: Bargaining Council for the Contract Cleaning Services Industry (KwaZulu-Natal) Main Collective Agreement, GN R.7296 in Government Gazette 54412, 27 March 2026 | B91: clauses 9, 10 and 12 | D91: REF-2026.04.01-BCCCI-RULES-r2 | E91: leave_rule_set | F91: Leave rules — CONTRACT_CLEANING / AREA_B — sick leave weeks equivalent | G91: 6,00 | H91: 2026-04-01 | J91: leave_rule_set:4:sick_leave_weeks_equivalent
A92: Basic Conditions of Employment Act 75 of 1997 | B92: s22(1)-(2). Commencement of Chapter 6. | C92: https://www.labour.gov.za/DocumentCenter/Acts/Basic%20Conditions%20of%20Employment/Act%20-%20Basic%20Conditions%20of%20Employment.pdf | D92: REF-2026.03.01-SICK-ACCRUAL | E92: statutory_parameter | F92: Statutory parameter SICK_LEAVE_FIRST_PERIOD_MONTHS (all sectors) — unit | G92: Months | H92: 1997-12-01 | J92: statutory_parameter:13:unit
A93: Basic Conditions of Employment Act 75 of 1997 | B93: s22(1)-(2). Commencement of Chapter 6. | C93: https://www.labour.gov.za/DocumentCenter/Acts/Basic%20Conditions%20of%20Employment/Act%20-%20Basic%20Conditions%20of%20Employment.pdf | D93: REF-2026.03.01-SICK-ACCRUAL | E93: statutory_parameter | F93: Statutory parameter SICK_LEAVE_FIRST_PERIOD_MONTHS (all sectors) — value | G93: 6,000000 | H93: 1997-12-01 | J93: statutory_parameter:13:value_numeric
A94: Basic Conditions of Employment Act 75 of 1997 | B94: s23(1). Commencement of Chapter 6. | C94: https://www.labour.gov.za/DocumentCenter/Acts/Basic%20Conditions%20of%20Employment/Act%20-%20Basic%20Conditions%20of%20Employment.pdf | D94: REF-2026.03.01-LEAVE | E94: statutory_parameter | F94: Statutory parameter SICK_CERTIFICATE_MAX_CONSECUTIVE_DAYS (all sectors) — unit | G94: Days | H94: 1997-12-01 | J94: statutory_parameter:12:unit
A95: Basic Conditions of Employment Act 75 of 1997 | B95: s23(1). Commencement of Chapter 6. | C95: https://www.labour.gov.za/DocumentCenter/Acts/Basic%20Conditions%20of%20Employment/Act%20-%20Basic%20Conditions%20of%20Employment.pdf | D95: REF-2026.03.01-LEAVE | E95: statutory_parameter | F95: Statutory parameter SICK_CERTIFICATE_MAX_CONSECUTIVE_DAYS (all sectors) — value | G95: 2,000000 | H95: 1997-12-01 | J95: statutory_parameter:12:value_numeric
A96: Basic Conditions of Employment Act 75 of 1997 | B96: s35(4)(a) | C96: https://www.gov.za/sites/default/files/gcis_document/201409/a75-97.pdf | D96: REF-2026.03.01-LEAVE-PAY | E96: statutory_parameter | F96: Statutory parameter VARIABLE_EARNINGS_AVERAGE_WEEKS (all sectors) — unit | G96: Weeks | H96: 1997-12-01 | J96: statutory_parameter:14:unit
A97: Basic Conditions of Employment Act 75 of 1997 | B97: s35(4)(a) | C97: https://www.gov.za/sites/default/files/gcis_document/201409/a75-97.pdf | D97: REF-2026.03.01-LEAVE-PAY | E97: statutory_parameter | F97: Statutory parameter VARIABLE_EARNINGS_AVERAGE_WEEKS (all sectors) — value | G97: 13,000000 | H97: 1997-12-01 | J97: statutory_parameter:14:value_numeric
A98: Basic Conditions of Employment Act 75 of 1997 | B98: s35, read with Form BCEA1A (Regulation 2), Summary of the Act | C98: https://www.wits.ac.za/media/wits-university/about-wits/documents/Form%20BCEA1A%20-%20Summary%20of%20the%20Act%20-%20English.pdf | D98: REF-2026.03.01-REMUNERATION | E98: statutory_parameter | F98: Statutory parameter MONTHLY_TO_WEEKLY_FACTOR (all sectors) — unit | G98: Ratio | H98: 1997-12-01 | J98: statutory_parameter:11:unit
A99: Basic Conditions of Employment Act 75 of 1997 | B99: s35, read with Form BCEA1A (Regulation 2), Summary of the Act | C99: https://www.wits.ac.za/media/wits-university/about-wits/documents/Form%20BCEA1A%20-%20Summary%20of%20the%20Act%20-%20English.pdf | D99: REF-2026.03.01-REMUNERATION | E99: statutory_parameter | F99: Statutory parameter MONTHLY_TO_WEEKLY_FACTOR (all sectors) — value | G99: 4,333333 | H99: 1997-12-01 | J99: statutory_parameter:11:value_numeric
A100: Basic Conditions of Employment Act 75 of 1997 | B100: s37(1)(a) | D100: REF-2026.03.01-NOTICE-BANDS-3 | E100: termination_notice_band | F100: Notice band 1 — all sectors, 0.00 months to 6.00 months — is contested | G100: No | J100: termination_notice_band:1:is_contested
A101: Basic Conditions of Employment Act 75 of 1997 | B101: s37(1)(a) | D101: REF-2026.03.01-NOTICE-BANDS-3 | E101: termination_notice_band | F101: Notice band 1 — all sectors, 0.00 months to 6.00 months — notice unit | G101: Weeks | J101: termination_notice_band:1:notice_unit
A102: Basic Conditions of Employment Act 75 of 1997 | B102: s37(1)(a) | D102: REF-2026.03.01-NOTICE-BANDS-3 | E102: termination_notice_band | F102: Notice band 1 — all sectors, 0.00 months to 6.00 months — notice value | G102: 1,00 | J102: termination_notice_band:1:notice_value
A103: Basic Conditions of Employment Act 75 of 1997 | B103: s37(1)(a) | D103: REF-2026.03.01-NOTICE-BANDS-3 | E103: termination_notice_band | F103: Notice band 1 — all sectors, 0.00 months to 6.00 months — service from inclusive | G103: Yes | J103: termination_notice_band:1:service_from_inclusive
A104: Basic Conditions of Employment Act 75 of 1997 | B104: s37(1)(a) | D104: REF-2026.03.01-NOTICE-BANDS-3 | E104: termination_notice_band | F104: Notice band 1 — all sectors, 0.00 months to 6.00 months — service from unit | G104: Months | J104: termination_notice_band:1:service_from_unit
A105: Basic Conditions of Employment Act 75 of 1997 | B105: s37(1)(a) | D105: REF-2026.03.01-NOTICE-BANDS-3 | E105: termination_notice_band | F105: Notice band 1 — all sectors, 0.00 months to 6.00 months — service from value | G105: 0,00 | J105: termination_notice_band:1:service_from_value
A106: Basic Conditions of Employment Act 75 of 1997 | B106: s37(1)(a) | D106: REF-2026.03.01-NOTICE-BANDS-3 | E106: termination_notice_band | F106: Notice band 1 — all sectors, 0.00 months to 6.00 months — service to inclusive | G106: Yes | J106: termination_notice_band:1:service_to_inclusive
A107: Basic Conditions of Employment Act 75 of 1997 | B107: s37(1)(a) | D107: REF-2026.03.01-NOTICE-BANDS-3 | E107: termination_notice_band | F107: Notice band 1 — all sectors, 0.00 months to 6.00 months — service to unit | G107: Months | J107: termination_notice_band:1:service_to_unit
A108: Basic Conditions of Employment Act 75 of 1997 | B108: s37(1)(a) | D108: REF-2026.03.01-NOTICE-BANDS-3 | E108: termination_notice_band | F108: Notice band 1 — all sectors, 0.00 months to 6.00 months — service to value | G108: 6,00 | J108: termination_notice_band:1:service_to_value
A109: Basic Conditions of Employment Act 75 of 1997 | B109: s37(1)(b) | D109: REF-2026.03.01-NOTICE-BANDS-3 | E109: termination_notice_band | F109: Notice band 2 — all sectors, 6.00 months to 1.00 years — is contested | G109: No | J109: termination_notice_band:2:is_contested
A110: Basic Conditions of Employment Act 75 of 1997 | B110: s37(1)(b) | D110: REF-2026.03.01-NOTICE-BANDS-3 | E110: termination_notice_band | F110: Notice band 2 — all sectors, 6.00 months to 1.00 years — notice unit | G110: Weeks | J110: termination_notice_band:2:notice_unit
A111: Basic Conditions of Employment Act 75 of 1997 | B111: s37(1)(b) | D111: REF-2026.03.01-NOTICE-BANDS-3 | E111: termination_notice_band | F111: Notice band 2 — all sectors, 6.00 months to 1.00 years — notice value | G111: 2,00 | J111: termination_notice_band:2:notice_value
... A123: Basic Conditions of Employment Act 75 of 1997 | B123: s37(1)(c)(i) | D123: REF-2026.03.01-NOTICE-BANDS-3 | E123: termination_notice_band | F123: Notice band 3 — all sectors, 1.00 years to open-ended — service from value | G123: 1,00 | J123: termination_notice_band:3:service_from_value
A124: Basic Conditions of Employment Act 75 of 1997 | B124: s40(c) | C124: https://www.gov.za/sites/default/files/gcis_document/201409/a75-97.pdf | D124: REF-2026.03.01-TERMINATION | E124: statutory_parameter | F124: Statutory parameter PRO_RATA_LEAVE_MIN_SERVICE_MONTHS (all sectors) — unit | G124: Months | H124: 1997-12-01 | J124: statutory_parameter:15:unit
A125: Basic Conditions of Employment Act 75 of 1997 | B125: s40(c) | C125: https://www.gov.za/sites/default/files/gcis_document/201409/a75-97.pdf | D125: REF-2026.03.01-TERMINATION | E125: statutory_parameter | F125: Statutory parameter PRO_RATA_LEAVE_MIN_SERVICE_MONTHS (all sectors) — value | G125: 4,000000 | H125: 1997-12-01 | J125: statutory_parameter:15:value_numeric
A126: Basic Conditions of Employment Act 75 of 1997 | B126: s43(1). Commencement of Chapter 6. | C126: https://www.labour.gov.za/DocumentCenter/Acts/Basic%20Conditions%20of%20Employment/Act%20-%20Basic%20Conditions%20of%20Employment.pdf | D126: REF-2026.03.01-EMPLOYMENT | E126: statutory_parameter | F126: Statutory parameter MINIMUM_EMPLOYMENT_AGE (all sectors) — unit | G126: Years | H126: 1997-12-01 | J126: statutory_parameter:10:unit
A127: Basic Conditions of Employment Act 75 of 1997 | B127: s43(1). Commencement of Chapter 6. | C127: https://www.labour.gov.za/DocumentCenter/Acts/Basic%20Conditions%20of%20Employment/Act%20-%20Basic%20Conditions%20of%20Employment.pdf | D127: REF-2026.03.01-EMPLOYMENT | E127: statutory_parameter | F127: Statutory parameter MINIMUM_EMPLOYMENT_AGE (all sectors) — value | G127: 15,000000 | H127: 1997-12-01 | J127: statutory_parameter:10:value_numeric
A128: Basic Conditions of Employment Act 75 of 1997 | B128: ss 20-27 | D128: REF-2026.03.01-RULES-r4 | E128: leave_rule_set | F128: Leave rules — all sectors — annual accrual days per month 5day | G128: 1,250 | H128: 2026-03-01 | J128: leave_rule_set:1:annual_accrual_days_per_month_5day
A129: Basic Conditions of Employment Act 75 of 1997 | B129: ss 20-27 | D129: REF-2026.03.01-RULES-r4 | E129: leave_rule_set | F129: Leave rules — all sectors — annual accrual days per month 6day | G129: 1,500 | H129: 2026-03-01 | J129: leave_rule_set:1:annual_accrual_days_per_month_6day
A130: Basic Conditions of Employment Act 75 of 1997 | B130: ss 20-27 | D130: REF-2026.03.01-RULES-r4 | E130: leave_rule_set | F130: Leave rules — all sectors — annual accrual ratio days worked | G130: 17 | H130: 2026-03-01 | J130: leave_rule_set:1:annual_accrual_ratio_days_worked
A131: Basic Conditions of Employment Act 75 of 1997 | B131: ss 20-27 | D131: REF-2026.03.01-RULES-r4 | E131: leave_rule_set | F131: Leave rules — all sectors — annual accrual ratio hours worked | G131: 17 | H131: 2026-03-01 | J131: leave_rule_set:1:annual_accrual_ratio_hours_worked
A132: Basic Conditions of Employment Act 75 of 1997 | B132: ss 20-27 | D132: REF-2026.03.01-RULES-r4 | E132: leave_rule_set | F132: Leave rules — all sectors — annual leave cycle months | G132: 12 | H132: 2026-03-01 | J132: leave_rule_set:1:annual_leave_cycle_months
A133: Basic Conditions of Employment Act 75 of 1997 | B133: ss 20-27 | D133: REF-2026.03.01-RULES-r4 | E133: leave_rule_set | F133: Leave rules — all sectors — annual leave days per cycle 5day | G133: 15,000 | H133: 2026-03-01 | J133: leave_rule_set:1:annual_leave_days_per_cycle_5day
A134: Basic Conditions of Employment Act 75 of 1997 | B134: ss 20-27 | D134: REF-2026.03.01-RULES-r4 | E134: leave_rule_set | F134: Leave rules — all sectors — annual leave days per cycle 6day | G134: 18,000 | H134: 2026-03-01 | J134: leave_rule_set:1:annual_leave_days_per_cycle_6day
A135: Basic Conditions of Employment Act 75 of 1997 | B135: ss 20-27 | D135: REF-2026.03.01-RULES-r4 | E135: leave_rule_set | F135: Leave rules — all sectors — annual leave forfeit months | G135: 6 | H135: 2026-03-01 | J135: leave_rule_set:1:annual_leave_forfeit_months
A136: Basic Conditions of Employment Act 75 of 1997 | B136: ss 20-27 | D136: REF-2026.03.01-RULES-r4 | E136: leave_rule_set | F136: Leave rules — all sectors — annual leave payable on termination | G136: Yes | H136: 2026-03-01 | J136: leave_rule_set:1:annual_leave_payable_on_termination
A137: Basic Conditions of Employment Act 75 of 1997 | B137: ss 20-27 | D137: REF-2026.03.01-RULES-r4 | E137: leave_rule_set | F137: Leave rules — all sectors — family resp min days per week | G137: 4 | H137: 2026-03-01 | J137: leave_rule_set:1:family_resp_min_days_per_week
A138: Basic Conditions of Employment Act 75 of 1997 | B138: ss 20-27 | D138: REF-2026.03.01-RULES-r4 | E138: leave_rule_set | F138: Leave rules — all sectors — family resp min service months | G138: 4 | H138: 2026-03-01 | J138: leave_rule_set:1:family_resp_min_service_months
A139: Basic Conditions of Employment Act 75 of 1997 | B139: ss 20-27 | D139: REF-2026.03.01-RULES-r4 | E139: leave_rule_set | F139: Leave rules — all sectors — family responsibility days | G139: 3 | H139: 2026-03-01 | J139: leave_rule_set:1:family_responsibility_days
... A177: Basic Conditions of Employment Act 75 of 1997 | B177: ss 9-18 and s9A | D177: REF-2026.03.01-RULES-r4 | E177: working_time_rule_set | F177: Working time rules — all sectors — weekly rest hours | G177: 36 | H177: 2026-03-01 | J177: working_time_rule_set:1:weekly_rest_hours
A178: Compensation Fund maximum amount of earnings, 2026/2027 assessment year (1 March 2026 - 28 February 2027) | D178: REF-2026.03.01-r2 | E178: statutory_parameter | F178: Statutory parameter COIDA_ANNUAL_CEILING (all sectors) — unit | G178: Rand | H178: 2026-03-01 | J178: statutory_parameter:6:unit
A179: Compensation Fund maximum amount of earnings, 2026/2027 assessment year (1 March 2026 - 28 February 2027) | D179: REF-2026.03.01-r2 | E179: statutory_parameter | F179: Statutory parameter COIDA_ANNUAL_CEILING (all sectors) — value | G179: R 668 000,00 | H179: 2026-03-01 | J179: statutory_parameter:6:value_numeric
A180: Determination under s6(2) of the Unemployment Insurance Contributions Act 4 of 2002, Government Gazette 44641 of 28 May 2021, effective 1 June 2021 | D180: REF-2026.03.01-r2 | E180: statutory_parameter | F180: Statutory parameter UIF_MONTHLY_CEILING (all sectors) — unit | G180: Rand | H180: 2021-06-01 | J180: statutory_parameter:3:unit
A181: Determination under s6(2) of the Unemployment Insurance Contributions Act 4 of 2002, Government Gazette 44641 of 28 May 2021, effective 1 June 2021 | D181: REF-2026.03.01-r2 | E181: statutory_parameter | F181: Statutory parameter UIF_MONTHLY_CEILING (all sectors) — value | G181: R 17 712,00 | H181: 2021-06-01 | J181: statutory_parameter:3:value_numeric
A182: GN 5970, GG 52232, March 2025 (Basic Conditions of Employment Act 75 of 1997, s6(3)) | D182: REF-2026.03.01-r2 | E182: statutory_parameter | F182: Statutory parameter BCEA_EARNINGS_THRESHOLD (all sectors) — unit | G182: Rand | H182: 2025-04-01 | I182: 2026-05-01 | J182: statutory_parameter:7:unit
A183: GN 5970, GG 52232, March 2025 (Basic Conditions of Employment Act 75 of 1997, s6(3)) | D183: REF-2026.03.01-r2 | E183: statutory_parameter | F183: Statutory parameter BCEA_EARNINGS_THRESHOLD (all sectors) — value | G183: R 261 748,45 | H183: 2025-04-01 | I183: 2026-05-01 | J183: statutory_parameter:7:value_numeric
A184: GN 7384, GG 54544, 17 April 2026 (Basic Conditions of Employment Act 75 of 1997, s6(3)) | D184: REF-2026.03.01-r2 | E184: statutory_parameter | F184: Statutory parameter BCEA_EARNINGS_THRESHOLD (all sectors) — unit | G184: Rand | H184: 2026-05-01 | J184: statutory_parameter:8:unit
A185: GN 7384, GG 54544, 17 April 2026 (Basic Conditions of Employment Act 75 of 1997, s6(3)) | D185: REF-2026.03.01-r2 | E185: statutory_parameter | F185: Statutory parameter BCEA_EARNINGS_THRESHOLD (all sectors) — value | G185: R 269 600,90 | H185: 2026-05-01 | J185: statutory_parameter:8:value_numeric
A186: GN R.7083, GG 54075, 3 February 2026 (National Minimum Wage Act 9 of 2018) | C186: https://www.gov.za/sites/default/files/gcis_document/202602/54075rg11941gon7083.pdf | D186: REF-2026.03.01-r2 | E186: minimum_wage_rate | F186: Minimum wage — all sectors, all hours — hourly rate | G186: R 30,23 | H186: 2026-03-01 | J186: minimum_wage_rate:1:hourly_rate
A187: GN R.7083, GG 54075, 3 February 2026 (National Minimum Wage Act 9 of 2018) | C187: https://www.gov.za/sites/default/files/gcis_document/202602/54075rg11941gon7083.pdf | D187: REF-2026.03.01-r2 | E187: minimum_wage_rate | F187: Minimum wage — DOMESTIC, all hours — hourly rate | G187: R 30,23 | H187: 2026-03-01 | J187: minimum_wage_rate:2:hourly_rate
A188: GN R.7083, GG 54075, 3 February 2026 (National Minimum Wage Act 9 of 2018) | C188: https://www.gov.za/sites/default/files/gcis_document/202602/54075rg11941gon7083.pdf | D188: REF-2026.03.01-r2 | E188: minimum_wage_rate | F188: Minimum wage — CONTRACT_CLEANING / AREA_A, all hours — hourly rate | G188: R 33,27 | H188: 2026-03-01 | J188: minimum_wage_rate:3:hourly_rate
A189: GN R.7083, GG 54075, 3 February 2026 (National Minimum Wage Act 9 of 2018) | C189: https://www.gov.za/sites/default/files/gcis_document/202602/54075rg11941gon7083.pdf | D189: REF-2026.03.01-r2 | E189: minimum_wage_rate | F189: Minimum wage — CONTRACT_CLEANING / AREA_A, all hours — monthly rate (45h) | G189: R 6 487,15 | H189: 2026-03-01 | J189: minimum_wage_rate:3:monthly_rate_45h
A190: GN R.7083, GG 54075, 3 February 2026 (National Minimum Wage Act 9 of 2018) | C190: https://www.gov.za/sites/default/files/gcis_document/202602/54075rg11941gon7083.pdf | D190: REF-2026.03.01-r2 | E190: minimum_wage_rate | F190: Minimum wage — CONTRACT_CLEANING / AREA_A, all hours — weekly rate (45h) | G190: R 1 497,15 | H190: 2026-03-01 | J190: minimum_wage_rate:3:weekly_rate_45h
A191: GN R.7083, GG 54075, 3 February 2026 (National Minimum Wage Act 9 of 2018) | C191: https://www.gov.za/sites/default/files/gcis_document/202602/54075rg11941gon7083.pdf | D191: REF-2026.03.01-r2 | E191: minimum_wage_rate | F191: Minimum wage — CONTRACT_CLEANING / AREA_C, all hours — hourly rate | G191: R 30,33 | H191: 2026-03-01 | J191: minimum_wage_rate:4:hourly_rate
A192: GN R.7083, GG 54075, 3 February 2026 (National Minimum Wage Act 9 of 2018) | C192: https://www.gov.za/sites/default/files/gcis_document/202602/54075rg11941gon7083.pdf | D192: REF-2026.03.01-r2 | E192: minimum_wage_rate | F192: Minimum wage — CONTRACT_CLEANING / AREA_C, all hours — monthly rate (45h) | G192: R 5 913,90 | H192: 2026-03-01 | J192: minimum_wage_rate:4:monthly_rate_45h
A193: GN R.7083, GG 54075, 3 February 2026 (National Minimum Wage Act 9 of 2018) | C193: https://www.gov.za/sites/default/files/gcis_document/202602/54075rg11941gon7083.pdf | D193: REF-2026.03.01-r2 | E193: minimum_wage_rate | F193: Minimum wage — CONTRACT_CLEANING / AREA_C, all hours — weekly rate (45h) | G193: R 1 364,85 | H193: 2026-03-01 | J193: minimum_wage_rate:4:weekly_rate_45h
A194: Public Holidays Act 36 of 1994 | B194: Schedule 1 | D194: REF-2026.03.01-r2 | E194: public_holiday | F194: Public holiday — Day of Reconciliation, 16 December 2026 — holiday date | G194: 16 December 2026 | J194: public_holiday:10:holiday_date
A195: Public Holidays Act 36 of 1994 | B195: Schedule 1 | D195: REF-2026.03.01-r2 | E195: public_holiday | F195: Public holiday — Day of Reconciliation, 16 December 2026 — is statutory | G195: Yes | J195: public_holiday:10:is_statutory
A196: Public Holidays Act 36 of 1994 | B196: Schedule 1 | D196: REF-2026.03.01-r2 | E196: public_holiday | F196: Public holiday — Day of Reconciliation, 16 December 2026 — name | G196: Day of Reconciliation | J196: public_holiday:10:name
A197: Public Holidays Act 36 of 1994 | B197: Schedule 1 | D197: REF-2026.03.01-r2 | E197: public_holiday | F197: Public holiday — Christmas Day, 25 December 2026 — holiday date | G197: 25 December 2026 | J197: public_holiday:11:holiday_date
A198: Public Holidays Act 36 of 1994 | B198: Schedule 1 | D198: REF-2026.03.01-r2 | E198: public_holiday | F198: Public holiday — Christmas Day, 25 December 2026 — is statutory | G198: Yes | J198: public_holiday:11:is_statutory
A199: Public Holidays Act 36 of 1994 | B199: Schedule 1 | D199: REF-2026.03.01-r2 | E199: public_holiday | F199: Public holiday — Christmas Day, 25 December 2026 — name | G199: Christmas Day | J199: public_holiday:11:name
A200: Public Holidays Act 36 of 1994 | B200: Schedule 1 | D200: REF-2026.03.01-r2 | E200: public_holiday | F200: Public holiday — Day of Goodwill, 26 December 2026 — holiday date | G200: 26 December 2026 | J200: public_holiday:12:holiday_date
A201: Public Holidays Act 36 of 1994 | B201: Schedule 1 | D201: REF-2026.03.01-r2 | E201: public_holiday | F201: Public holiday — Day of Goodwill, 26 December 2026 — is statutory | G201: Yes | J201: public_holiday:12:is_statutory
...
